a38/__init__.py
a38/builder.py
a38/codec.py
a38/consts.py
a38/crypto.py
a38/diff.py
a38/fattura.py
a38/fattura_semplificata.py
a38/fields.py
a38/models.py
a38/render.py
a38/traversal.py
a38/trustedlist.py
a38/validation.py
a38-0.1.8.data/scripts/a38tool
a38-0.1.8.dist-info/LICENSE
a38-0.1.8.dist-info/METADATA
a38-0.1.8.dist-info/WHEEL
a38-0.1.8.dist-info/top_level.txt
a38-0.1.8.dist-info/RECORD
