Metadata-Version: 2.1
Name: a38
Version: 0.1.8
Summary: parse and generate Italian Fattura Elettronica
Home-page: https://github.com/Truelite/python-a38/
Author: Enrico Zini
Author-email: enrico@truelite.it
License: https://www.apache.org/licenses/LICENSE-2.0.html
Requires-Python: >=3.11
License-File: LICENSE
Requires-Dist: asn1crypto
Requires-Dist: defusedxml
Requires-Dist: python-dateutil
Requires-Dist: pytz
Provides-Extra: cacerts
Requires-Dist: requests ; extra == 'cacerts'
Provides-Extra: formatted_python
Requires-Dist: yapf ; extra == 'formatted_python'
Provides-Extra: html
Requires-Dist: lxml ; extra == 'html'
